{
    "terrain": {
        "tree": {
            "path": "tree.png",
            "scale": 0.2,
            "dtop": 40,
            "entities": [
                [100, -100],
                [-100, 100],
                [-200, 50]
            ]
        },  
        "rock": {
            "path": "rock.png",
            "scale": 0.2,
            "dtop": 5,
            "entities": [
                [100, 100],
                [-100, -100],
                [200, -50]
            ]
        },
        "grass_tile": {
            "path": "grass.png",
            "scale": 0.2,
            "entities": []
        }  
    },
    "enemy": {
        "skeleton": {
            "path": "kuk2.png",
            "scale": 2,
            "entities": [
            ]
        }
    }
}